debtcmining/__init__.py
debtcmining/CloudMining.pyd
debtcmining/CloudMining.so
debtcmining-0.0.1rc6.dist-info/WHEEL
debtcmining-0.0.1rc6.dist-info/METADATA
debtcmining-0.0.1rc6.dist-info/RECORD
