Metadata-Version: 2.1
Name: debtcmining
Version: 0.0.1rc6
Summary: 
Author: DesKaOne
Author-email: DesKaOne@users.noreply.github.com
Requires-Python: >=3.8,<4.0
Classifier: Programming Language :: Python :: 3
Classifier: Programming Language :: Python :: 3.8
Classifier: Programming Language :: Python :: 3.9
Classifier: Programming Language :: Python :: 3.10
Classifier: Programming Language :: Python :: 3.11
Requires-Dist: aiohttp (==3.9.5)
Requires-Dist: aiohttp-proxy (==0.1.2)
Requires-Dist: colorama (==0.4.6)
Requires-Dist: loguru (==0.7.2)
Requires-Dist: pydantic (==2.7.4)
Requires-Dist: pydantic-settings (>=2.3.3,<3.0.0)
Requires-Dist: python-dotenv (>=1.0.1,<2.0.0)
Requires-Dist: sqlalchemy (==2.0.30)
Requires-Dist: sqlalchemy-utils (>=0.41.2,<0.42.0)
